.gitignore
.pypirc
Dockerfile
LICENCE
MANIFEST.in
README.rst
init_data.json
manage.py
requirements.txt
runtests.py
setup.py
BaseFunctionModule/__init__.py
BaseFunctionModule/asgi.py
BaseFunctionModule/settings.py
BaseFunctionModule/urls.py
BaseFunctionModule/wsgi.py
base_system/__init__.py
base_system/admin.py
base_system/apps.py
base_system/auth.py
base_system/examination_dic.json
base_system/export_viewset.py
base_system/inspdic.json
base_system/models.py
base_system/serializers.py
base_system/tests.py
base_system/urls.py
base_system/views.py
base_system/viewsets.py
base_system.egg-info/PKG-INFO
base_system.egg-info/SOURCES.txt
base_system.egg-info/dependency_links.txt
base_system.egg-info/not-zip-safe
base_system.egg-info/requires.txt
base_system.egg-info/top_level.txt
base_system/__pycache__/__init__.cpython-39.pyc
base_system/__pycache__/admin.cpython-39.pyc
base_system/__pycache__/apps.cpython-39.pyc
base_system/__pycache__/export_viewset.cpython-39.pyc
base_system/__pycache__/models.cpython-39.pyc
base_system/__pycache__/serializers.cpython-39.pyc
base_system/__pycache__/tests.cpython-39.pyc
base_system/__pycache__/urls.cpython-39.pyc
base_system/__pycache__/views.cpython-39.pyc
base_system/__pycache__/viewsets.cpython-39.pyc
base_system/migrations/0001_initial.py
base_system/migrations/0002_drugdirectory_code_medu_cur.py
base_system/migrations/0003_alter_extragroup_hospital.py
base_system/migrations/0004_alter_extragroup_role_name.py
base_system/migrations/0005_expensetype.py
base_system/migrations/0006_alter_doctor_photo.py
base_system/migrations/0007_auto_20230512_1742.py
base_system/migrations/__init__.py
base_system/migrations/__pycache__/0001_initial.cpython-39.pyc
base_system/migrations/__pycache__/0002_drugdirectory_code_medu_cur.cpython-39.pyc
base_system/migrations/__pycache__/0003_alter_extragroup_hospital.cpython-39.pyc
base_system/migrations/__pycache__/0004_alter_extragroup_role_name.cpython-39.pyc
base_system/migrations/__pycache__/0005_expensetype.cpython-39.pyc
base_system/migrations/__pycache__/0006_alter_doctor_photo.cpython-39.pyc
base_system/migrations/__pycache__/0007_auto_20230512_1742.cpython-39.pyc
